zoinks/__init__.py
zoinks/__main__.py
zoinks/exceptions.py
zoinks/exit_codes.py
zoinks-0.0.8.dist-info/LICENSE
zoinks-0.0.8.dist-info/METADATA
zoinks-0.0.8.dist-info/WHEEL
zoinks-0.0.8.dist-info/entry_points.txt
zoinks-0.0.8.dist-info/top_level.txt
zoinks-0.0.8.dist-info/RECORD
