Metadata-Version: 2.1
Name: zoinks
Version: 0.0.8
Summary: Zoinks: a command-line utility to retrieve Zotero record values
Home-page: https://github.com/mhucka/zoinks
Author: Mike Hucka
Author-email: mhucka@caltech.edu
License: BSD 3-clause license
Project-URL: Source Code, https://github.com/mhucka/zoinks
Project-URL: Bug Tracker, https://github.com/mhucka/zoinks/issues
Keywords: Python,applications
Classifier: Development Status :: 3 - Alpha
Classifier: Environment :: Console
Classifier: License :: OSI Approved :: BSD License
Classifier: Intended Audience :: Science/Research
Classifier: Operating System :: MacOS :: MacOS X
Classifier: Programming Language :: Python
Classifier: Programming Language :: Python :: 3.9
Requires-Python: >=3.9
License-File: LICENSE
Requires-Dist: aenum ==3.1.15
Requires-Dist: appscript ==1.2.2
Requires-Dist: commonpy ==1.13.0
Requires-Dist: plac ==1.4.2
Requires-Dist: requests ==2.31.0
Requires-Dist: sidetrack ==2.0.1
Requires-Dist: setuptools >=69.0.0
Requires-Dist: uritools ==4.0.2
